SchoginiAI/__init__.py
SchoginiAI/main.py
SchoginiAI-0.2.4.dist-info/LICENSE
SchoginiAI-0.2.4.dist-info/METADATA
SchoginiAI-0.2.4.dist-info/WHEEL
SchoginiAI-0.2.4.dist-info/top_level.txt
SchoginiAI-0.2.4.dist-info/RECORD
