Metadata-Version: 2.1
Name: SchoginiAI
Version: 0.2.4
Summary: A sample AI toolkit by Schogini Systems with Retrieval-Augmented Generation (RAG).
Home-page: https://github.com/schogini/SchoginiAI
Author: Sreeprakash Neelakantan
Author-email: schogini@gmail.com
Classifier: Programming Language :: Python :: 3
Classifier: License :: OSI Approved :: MIT License
Classifier: Operating System :: OS Independent
Requires-Python: >=3.7
License-File: LICENSE
Requires-Dist: langchain>=0.3.14
Requires-Dist: langchain-community>=0.3.14
Requires-Dist: openai>=1.59.3
Requires-Dist: tiktoken>=0.8.0
Requires-Dist: faiss-cpu>=1.9.0.post1
Requires-Dist: langchain-openai
Requires-Dist: langchain-chroma
Requires-Dist: langchain-pinecone
Requires-Dist: langchain_experimental
Requires-Dist: chromadb
Requires-Dist: pinecone-client
Requires-Dist: pypdf
Requires-Dist: unstructured
